jupyter_viz_extension/__init__.py
jupyter_viz_extension/_version.py
jupyter_viz_extension/cmd.py
jupyter_viz_extension/model.py
jupyter_viz_extension/proxy.py
jupyter_viz_extension/types.py
jupyter_viz_extension/configurations/__init__.py
jupyter_viz_extension/configurations/desktop.py
jupyter_viz_extension/configurations/jsc/__init__.py
jupyter_viz_extension/configurations/jsc/paraview_juwelsbooster.in
jupyter_viz_extension/handlers/__init__.py
jupyter_viz_extension/handlers/paraview.py
jupyter_viz_extension/handlers/trame.py
jupyter_viz_extension/handlers/user.py
jupyter_viz_extension-0.5.1.data/data/etc/jupyter/jupyter_server_config.d/jupyter_viz_extension.json
jupyter_viz_extension-0.5.1.data/data/share/jupyter/labextensions/jupyter-viz-extension/package.json
jupyter_viz_extension-0.5.1.data/data/share/jupyter/labextensions/jupyter-viz-extension/schemas/jupyter-viz-extension/package.json.orig
jupyter_viz_extension-0.5.1.data/data/share/jupyter/labextensions/jupyter-viz-extension/schemas/jupyter-viz-extension/plugin.json
jupyter_viz_extension-0.5.1.data/data/share/jupyter/labextensions/jupyter-viz-extension/static/105.ffde1c47bd1e933ab23d.js
jupyter_viz_extension-0.5.1.data/data/share/jupyter/labextensions/jupyter-viz-extension/static/233.7eef7160982e3f60d9aa.js
jupyter_viz_extension-0.5.1.data/data/share/jupyter/labextensions/jupyter-viz-extension/static/614.09d7b44083eed0867e6f.js
jupyter_viz_extension-0.5.1.data/data/share/jupyter/labextensions/jupyter-viz-extension/static/728.a6b7827fe5278268b7fe.js
jupyter_viz_extension-0.5.1.data/data/share/jupyter/labextensions/jupyter-viz-extension/static/remoteEntry.03fb68556c889a2f4798.js
jupyter_viz_extension-0.5.1.data/data/share/jupyter/labextensions/jupyter-viz-extension/static/style.js
jupyter_viz_extension-0.5.1.data/data/share/jupyter/labextensions/jupyter-viz-extension/static/third-party-licenses.json
jupyter_viz_extension-0.5.1.data/data/share/jupyter/labextensions/jupyter-viz-extension/install.json
jupyter_viz_extension-0.5.1.dist-info/METADATA
jupyter_viz_extension-0.5.1.dist-info/WHEEL
jupyter_viz_extension-0.5.1.dist-info/licenses/LICENSE
jupyter_viz_extension-0.5.1.dist-info/RECORD
