Metadata-Version: 2.3
Name: jupyter_viz_extension
Version: 0.5.1
Dynamic: Keywords
Summary: A JupyterLab extension.
Project-URL: Homepage, https://github.com/jwindgassen/jupyter_viz_extension
Project-URL: Bug Tracker, https://github.com/jwindgassen/jupyter_viz_extension/issues
Project-URL: Repository, https://github.com/jwindgassen/jupyter_viz_extension.git
Author-email: Jonathan Windgassen <j.windgassen@fz-juelich.de>
License: BSD 3-Clause License
License-File: LICENSE
Classifier: Framework :: Jupyter
Classifier: Framework :: Jupyter :: JupyterLab
Classifier: Framework :: Jupyter :: JupyterLab :: 4
Classifier: Framework :: Jupyter :: JupyterLab :: Extensions
Classifier: Framework :: Jupyter :: JupyterLab :: Extensions :: Prebuilt
Classifier: License :: OSI Approved :: BSD License
Classifier: Programming Language :: Python
Classifier: Programming Language :: Python :: 3
Classifier: Programming Language :: Python :: 3.10
Classifier: Programming Language :: Python :: 3.11
Classifier: Programming Language :: Python :: 3.12
Requires-Python: >=3.10
Requires-Dist: jupyter-server-proxy>=4.1
Requires-Dist: jupyter-server<3,>=2.0.1
